autoresevaluator/__init__.py
autoresevaluator/dataset/cv/cifar10.py
autoresevaluator/dataset/tabledata/titanic.py
autoresevaluator/llm/anthropic.py
autoresevaluator/llm/google.py
autoresevaluator/llm/openai.py
autoresevaluator/main.py
autoresevaluator/metrix/binary_classification.py
autoresevaluator/metrix/multiclass_classificatio.py
autoresevaluator/metrix/regression.py
autoresevaluator/train/dataloader.py
autoresevaluator/train/dataset.py
autoresevaluator/train/optuna.py
autoresevaluator/utils/codefix.py
autoresevaluator/utils/load_method.py
autoresevaluator/utils/log_config.py
autoresevaluator-0.1.11.dist-info/LICENSE
autoresevaluator-0.1.11.dist-info/METADATA
autoresevaluator-0.1.11.dist-info/WHEEL
autoresevaluator-0.1.11.dist-info/RECORD
