Metadata-Version: 2.1
Name: autoresevaluator
Version: 0.1.11
Summary: 
Author: toma tanaka
Author-email: ulti4929@gmail.com
Requires-Python: >=3.9,<4.0
Classifier: Programming Language :: Python :: 3
Classifier: Programming Language :: Python :: 3.9
Classifier: Programming Language :: Python :: 3.10
Classifier: Programming Language :: Python :: 3.11
Requires-Dist: anthropic (>=0.18.1,<0.19.0)
Requires-Dist: google-generativeai (>=0.4.0,<0.5.0)
Requires-Dist: openai (>=1.11.1,<2.0.0)
Requires-Dist: optuna (>=3.5.0,<4.0.0)
Requires-Dist: torch (>=2.2.0,<3.0.0)
Requires-Dist: torchvision (>=0.17.0,<0.18.0)
Requires-Dist: tqdm (>=4.66.1,<5.0.0)
